generic_connection_pool/__init__.py
generic_connection_pool/asyncio/__init__.py
generic_connection_pool/asyncio/locks.py
generic_connection_pool/asyncio/pool.py
generic_connection_pool/asyncio/utils.py
generic_connection_pool/common.py
generic_connection_pool/contrib/__init__.py
generic_connection_pool/contrib/asyncpg.py
generic_connection_pool/contrib/psycopg2.py
generic_connection_pool/contrib/socket.py
generic_connection_pool/contrib/socket_async.py
generic_connection_pool/contrib/unix.py
generic_connection_pool/contrib/unix_async.py
generic_connection_pool/exceptions.py
generic_connection_pool/py.typed
generic_connection_pool/rankmap.py
generic_connection_pool/threading/__init__.py
generic_connection_pool/threading/locks.py
generic_connection_pool/threading/pool.py
generic_connection_pool-0.7.0.dist-info/LICENSE
generic_connection_pool-0.7.0.dist-info/METADATA
generic_connection_pool-0.7.0.dist-info/WHEEL
generic_connection_pool-0.7.0.dist-info/RECORD
