Metadata-Version: 2.1
Name: generic-connection-pool
Version: 0.7.0
Summary: generic connection pool
Home-page: https://github.com/dapper91/generic-connection-pool
License: Unlicense
Keywords: pool,connection-pool,asyncio,socket,tcp
Author: Dmitry Pershin
Author-email: dapper1291@gmail.com
Requires-Python: >=3.9
Classifier: Development Status :: 5 - Production/Stable
Classifier: Intended Audience :: Developers
Classifier: License :: OSI Approved
Classifier: License :: Public Domain
Classifier: Natural Language :: English
Classifier: Operating System :: OS Independent
Classifier: Programming Language :: Python :: 3
Classifier: Programming Language :: Python :: 3.9
Classifier: Programming Language :: Python :: 3.10
Classifier: Programming Language :: Python :: 3.11
Classifier: Programming Language :: Python :: 3.12
Classifier: Topic :: Database
Classifier: Topic :: Internet :: WWW/HTTP
Classifier: Topic :: Software Development :: Libraries
Classifier: Topic :: System :: Networking
Classifier: Typing :: Typed
Provides-Extra: asyncpg
Provides-Extra: docs
Provides-Extra: psycopg2
Requires-Dist: Sphinx (>=6.2.1,<7.0.0) ; extra == "docs"
Requires-Dist: asyncpg (>=0.29.0,<0.30.0) ; extra == "asyncpg"
Requires-Dist: furo (>=2023.7.26,<2024.0.0) ; extra == "docs"
Requires-Dist: psycopg2 (>=2.9.5) ; extra == "psycopg2"
Requires-Dist: sphinx-copybutton (>=0.5.2,<0.6.0) ; extra == "docs"
Requires-Dist: sphinx_design (>=0.5.0,<0.6.0) ; extra == "docs"
Requires-Dist: toml (>=0.10.2,<0.11.0) ; extra == "docs"
Project-URL: Documentation, https://generic-connection-pool.readthedocs.io
Project-URL: Repository, https://github.com/dapper91/generic-connection-pool
